setup.py
tcp_messages/__init__.py
tcp_messages/connection.py
tcp_messages/message.py
tcp_messages/message_client.py
tcp_messages/message_event.py
tcp_messages/message_list.py
tcp_messages/message_server.py
tcp_messages/router.py
tcp_messages/util.py
tcp_messages.egg-info/PKG-INFO
tcp_messages.egg-info/SOURCES.txt
tcp_messages.egg-info/dependency_links.txt
tcp_messages.egg-info/not-zip-safe
tcp_messages.egg-info/requires.txt
tcp_messages.egg-info/top_level.txt