Metadata-Version: 2.1
Name: tcp-messages
Version: 1.0.41
Summary: create json services easily
Home-page: UNKNOWN
Author: german espinosa
Author-email: germanespinosa@gmail.com
License: MIT
Platform: UNKNOWN
